ingestion_app_new/__init__.py
ingestion_app_new/my_cli_app.py
ingestion_app_new/process_data.py
ingestion_app_new-0.7.dist-info/METADATA
ingestion_app_new-0.7.dist-info/WHEEL
ingestion_app_new-0.7.dist-info/entry_points.txt
ingestion_app_new-0.7.dist-info/top_level.txt
ingestion_app_new-0.7.dist-info/RECORD
