Metadata-Version: 2.1
Name: ingestion-app-new
Version: 0.7
Requires-Dist: click
